pytrnsys_gui-0.10.15.data/data/pytrnsys_gui_data/examples/PvAshpDhwShMfh/DdckPlaceHolderValues.json
pytrnsys_gui-0.10.15.data/data/pytrnsys_gui_data/examples/PvAshpDhwShMfh/PvAshpDhwShMfh.json
pytrnsys_gui-0.10.15.data/data/pytrnsys_gui_data/examples/PvAshpDhwShMfh/PvAshpDhwShMfh.pdf
pytrnsys_gui-0.10.15.data/data/pytrnsys_gui_data/examples/PvAshpDhwShMfh/latexNames.json
pytrnsys_gui-0.10.15.data/data/pytrnsys_gui_data/examples/PvAshpDhwShMfh/process.config
pytrnsys_gui-0.10.15.data/data/pytrnsys_gui_data/examples/PvAshpDhwShMfh/process_PvAshpDhwShMfh.py
pytrnsys_gui-0.10.15.data/data/pytrnsys_gui_data/examples/PvAshpDhwShMfh/run.config
pytrnsys_gui-0.10.15.data/data/pytrnsys_gui_data/examples/PvAshpDhwShMfh/ddck/Ashp/HP08L-M-BC.ddck
pytrnsys_gui-0.10.15.data/data/pytrnsys_gui_data/examples/PvAshpDhwShMfh/ddck/Ashp/type977.ddck
pytrnsys_gui-0.10.15.data/data/pytrnsys_gui_data/examples/PvAshpDhwShMfh/ddck/HxDhw/const_eff_hx_dhw_contr.ddck
pytrnsys_gui-0.10.15.data/data/pytrnsys_gui_data/examples/PvAshpDhwShMfh/ddck/Pv/elDemand.ddck
pytrnsys_gui-0.10.15.data/data/pytrnsys_gui_data/examples/PvAshpDhwShMfh/ddck/Pv/fronius_symo_inverter.ddck
pytrnsys_gui-0.10.15.data/data/pytrnsys_gui_data/examples/PvAshpDhwShMfh/ddck/Pv/grid_connection.ddck
pytrnsys_gui-0.10.15.data/data/pytrnsys_gui_data/examples/PvAshpDhwShMfh/ddck/Pv/sunskin_roof_module_eternit.ddck
pytrnsys_gui-0.10.15.data/data/pytrnsys_gui_data/examples/PvAshpDhwShMfh/ddck/Pv/type194.ddck
pytrnsys_gui-0.10.15.data/data/pytrnsys_gui_data/examples/PvAshpDhwShMfh/ddck/Pv/type194/database/140911_FRONIUS_SYMO_Inverter.dat
pytrnsys_gui-0.10.15.data/data/pytrnsys_gui_data/examples/PvAshpDhwShMfh/ddck/RadFloor/internal_gains.ddck
pytrnsys_gui-0.10.15.data/data/pytrnsys_gui_data/examples/PvAshpDhwShMfh/ddck/RadFloor/mfb30_2020.ddck
pytrnsys_gui-0.10.15.data/data/pytrnsys_gui_data/examples/PvAshpDhwShMfh/ddck/RadFloor/type1792.ddck
pytrnsys_gui-0.10.15.dist-info/LICENSE
pytrnsys_gui-0.10.15.dist-info/METADATA
pytrnsys_gui-0.10.15.dist-info/WHEEL
pytrnsys_gui-0.10.15.dist-info/entry_points.txt
pytrnsys_gui-0.10.15.dist-info/top_level.txt
pytrnsys_gui-0.10.15.dist-info/RECORD
