Metadata-Version: 2.1
Name: pytrnsys-gui
Version: 0.10.15
Summary: A GUI for Trnsys
Home-page: https://github.com/SPF-OST/pytrnsys
Author: Institute for Solar Technology (SPF), OST Rapperswil
Author-email: martin.neugebauer@ost.ch
License: UNKNOWN
Platform: UNKNOWN
Classifier: Programming Language :: Python :: 3
Classifier: License :: OSI Approved :: MIT License
Classifier: Operating System :: OS Independent
Requires-Python: >=3.9
License-File: LICENSE
Requires-Dist: pytrnsys
Requires-Dist: PyQT5
Requires-Dist: matplotlib
Requires-Dist: numpy
Requires-Dist: pandas
Requires-Dist: bokeh
Requires-Dist: dataclasses-jsonschema
Requires-Dist: appdirs
Requires-Dist: Jinja2
